easyclasses
