Metadata-Version: 2.1
Name: easyclasses
Version: 1.0.1
Summary: Lightweight dataclass library.
Author: ZeroIntensity
Author-email: <zintensitydev@gmail.com>
License: MIT
Project-URL: Source, https://github.com/ZeroIntensity/easyclasses
Keywords: python,dataclasses,performance
Platform: UNKNOWN
Classifier: Programming Language :: Python :: 3.6
Classifier: Programming Language :: Python :: 3.7
Classifier: Programming Language :: Python :: 3.8
Classifier: Programming Language :: Python :: 3.9
Classifier: Programming Language :: Python :: 3.10
Classifier: Programming Language :: Python :: 3.11
